py_trans/__init__.py
py_trans/async_translator.py
py_trans/errors.py
py_trans/extras.py
py_trans/translator.py
py_trans/data/languages.json
py_trans/data/version.json
py_trans-0.6.1.dist-info/LICENSE
py_trans-0.6.1.dist-info/METADATA
py_trans-0.6.1.dist-info/WHEEL
py_trans-0.6.1.dist-info/top_level.txt
py_trans-0.6.1.dist-info/RECORD
