Metadata-Version: 2.1
Name: py-trans
Version: 0.6.1
Summary: Free python library to translate text to different languages.
Home-page: https://github.com/Itz-fork/py-trans
Download-URL: https://github.com/Itz-fork/py-trans/releases/tag/py-trans-pypi-v0.6.1
Author: Itz-fork
Author-email: git.itzfork@gmail.com
License: MIT
Keywords: google translate,text translator,translator,py-trans
Classifier: Development Status :: 5 - Production/Stable
Classifier: Intended Audience :: Developers
Classifier: Topic :: Education
Classifier: License :: OSI Approved :: MIT License
Classifier: Programming Language :: Python :: 3
Classifier: Programming Language :: Python :: 3.4
Classifier: Programming Language :: Python :: 3.5
Classifier: Programming Language :: Python :: 3.6
Classifier: Programming Language :: Python :: 3.9
Classifier: Programming Language :: Python :: 3.10
Classifier: Programming Language :: Python :: 3.11
License-File: LICENSE
Requires-Dist: requests
Requires-Dist: aiohttp
